CHANGES.txt
README.txt
setup.py
l3/__init__.py
l3.egg-info/PKG-INFO
l3.egg-info/SOURCES.txt
l3.egg-info/dependency_links.txt
l3.egg-info/not-zip-safe
l3.egg-info/top_level.txt