Metadata-Version: 1.1
Name: l3
Version: 1.0
Summary: level3 api
Home-page: https://github.com/vangheem/l3
Author: Nathan Van Gheem
Author-email: nathan@vangheem.us
License: UNKNOWN
Keywords: level3 l3
Platform: UNKNOWN
Classifier: Programming Language :: Python
Classifier: Topic :: Internet :: WWW/HTTP
